PracticProject/__init__.py
PracticProject/big_number.py
practicproject-1.0.dist-info/METADATA
practicproject-1.0.dist-info/WHEEL
practicproject-1.0.dist-info/top_level.txt
practicproject-1.0.dist-info/RECORD
