Metadata-Version: 2.4
Name: PracticProject
Version: 1.0
Summary: Addition, subtraction and comparison of numbers.
Home-page: https://github.com/Maxitot/PracticProject
Author: Maxitot
Author-email: maximkafom6@gmail.com
Project-URL: GitHub, https://github.com/Maxitot/PracticProject
Keywords: files speedfiles
Classifier: Programming Language :: Python :: 3.11
Classifier: License :: OSI Approved :: MIT License
Classifier: Operating System :: OS Independent
Requires-Python: >=3.6
Requires-Dist: requests>=2.25.1
Dynamic: author
Dynamic: author-email
Dynamic: classifier
Dynamic: description
Dynamic: description-content-type
Dynamic: home-page
Dynamic: keywords
Dynamic: project-url
Dynamic: requires-dist
Dynamic: requires-python
Dynamic: summary
